LICENSE.txt
README.md
setup.cfg
setup.py
discordwebhook/__init__.py
discordwebhook/allowedmentions.py
discordwebhook/attachment.py
discordwebhook/author.py
discordwebhook/cache.py
discordwebhook/embed.py
discordwebhook/errors.py
discordwebhook/file.py
discordwebhook/http.py
discordwebhook/message.py
discordwebhook/versions.py
discordwebhook/webhook.py
discordwebhook.py.egg-info/PKG-INFO
discordwebhook.py.egg-info/SOURCES.txt
discordwebhook.py.egg-info/dependency_links.txt
discordwebhook.py.egg-info/requires.txt
discordwebhook.py.egg-info/top_level.txt