Metadata-Version: 2.1
Name: discordwebhook.py
Version: 1.1.2
Summary: Easily using discord webhooks in python - asynchronous and synchronous - documented at https://discordwebhook.readthedocs.io/en/latest/
Home-page: https://github.com/Coolo22/discordwebhook.py
Author: Coolo2
Author-email: itsxcoolo2@gmail.com
License: MIT
Download-URL: https://github.com/Coolo22/discordwebhook.py/raw/master/Archive/discordwebhook.py-1.1.2.tar.gz
Project-URL: Documentation, https://discordwebhook.readthedocs.io/en/latest
Project-URL: Issue tracker, https://github.com/Coolo22/discordwebhook.py/issues
Keywords: discord,webhook,python,api,post,asynchronous,synchronous
Platform: UNKNOWN
Classifier: Development Status :: 5 - Production/Stable
Classifier: Intended Audience :: Developers
Classifier: Topic :: Software Development :: Build Tools
Classifier: License :: OSI Approved :: MIT License
Classifier: Programming Language :: Python :: 3
Classifier: Programming Language :: Python :: 3.5
Classifier: Programming Language :: Python :: 3.6
Classifier: Programming Language :: Python :: 3.7
Classifier: Programming Language :: Python :: 3.8
Classifier: Programming Language :: Python :: 3.9
Classifier: Programming Language :: Python :: 3.10
License-File: LICENSE.txt
